astro_pi_orbit/__init__.py
astro_pi_orbit/telemetry.py
astro_pi_orbit-2.0.0.dist-info/LICENSE
astro_pi_orbit-2.0.0.dist-info/METADATA
astro_pi_orbit-2.0.0.dist-info/WHEEL
astro_pi_orbit-2.0.0.dist-info/top_level.txt
astro_pi_orbit-2.0.0.dist-info/RECORD
