Metadata-Version: 2.1
Name: astro_pi_orbit
Version: 2.0.0
Summary: Module for interfacing with the Astro Pi
Author-email: Ben Nuttall <ben@bennuttall.com>, George Boukeas <boukeas@gmail.com>, Geraint Ballinger <G3zz@users.noreply.github.com>
License: MIT License
Classifier: Programming Language :: Python :: 3
Classifier: Operating System :: OS Independent
Requires-Python: >=3.7
License-File: LICENSE
Requires-Dist: skyfield
